qbert/__init__.py
qbert/enums.py
qbert/piccolo_app.py
qbert/piccolo_migrations/__init__.py
qbert/piccolo_migrations/initial.py
qbert/queue.py
qbert/tables.py
qbert-0.1.7.dist-info/LICENSE
qbert-0.1.7.dist-info/WHEEL
qbert-0.1.7.dist-info/METADATA
qbert-0.1.7.dist-info/RECORD
