Metadata-Version: 2.1
Name: qbert
Version: 0.1.7
Summary: a dead simple task queue backed by postgres
Home-page: https://github.com/backwardspy/qbert
Author: backwardspy
Author-email: backwardspy@gmail.com
Requires-Python: >=3.10,<4.0
Classifier: Programming Language :: Python :: 3
Classifier: Programming Language :: Python :: 3.10
Requires-Dist: piccolo[orjson,postgres] (>=0.74.4)
Requires-Dist: pydantic (>=1.9.1,<2.0.0)
Requires-Dist: ulid-py (>=1.1.0,<2.0.0)
Project-URL: Repository, https://github.com/backwardspy/qbert
